rtsprofile/component_group.py
rtsprofile/component.py
rtsprofile/composite_type.py
rtsprofile/config_set.py
rtsprofile/direction.py
rtsprofile/exceptions.py
rtsprofile/exec_context.py
rtsprofile/location.py
rtsprofile/message_sending.py
rtsprofile/participant.py
rtsprofile/ports.py
rtsprofile/rts_profile.py
rtsprofile/utils.py
rtsprofile/port_connectors.py
rtsprofile/targets.py
rtsprofile/__init__.py
rtsprofile-4.1.0.dist-info/zip-safe
rtsprofile-4.1.0.dist-info/top_level.txt
rtsprofile-4.1.0.dist-info/METADATA
rtsprofile-4.1.0.dist-info/DESCRIPTION.rst
rtsprofile-4.1.0.dist-info/metadata.json
rtsprofile-4.1.0.dist-info/WHEEL
rtsprofile-4.1.0.dist-info/RECORD
