Metadata-Version: 2.0
Name: rtsprofile
Version: 4.1.0
Summary: Library to read, manipulate and write RT system profiles using the RTSProfile XML schema.
Home-page: http://github.com/gbiggs/rtsprofile
Author: Geoffrey Biggs
Author-email: geoffrey.biggs@aist.go.jp
License: LGPL3
Platform: UNKNOWN
Classifier: Development Status :: 5 - Production/Stable
Classifier: Intended Audience :: Developers
Classifier: License :: OSI Approved :: GNU Lesser General Public License v3 (LGPLv3)
Classifier: Natural Language :: English
Classifier: Operating System :: OS Independent
Classifier: Programming Language :: Python :: 2.7
Classifier: Topic :: Software Development
